[{"timestamp":1622630794997,"files":[{"filename":"bundle.*****.esm.js","previous":187176,"size":186251,"diff":-925},{"filename":"polyfills.*****.esm.js","previous":2182,"size":2182,"diff":0},{"filename":"sw-esm.js","previous":11287,"size":11285,"diff":-2},{"filename":"index.html","previous":1269,"size":1269,"diff":0},{"filename":"200.html","previous":1269,"size":1269,"diff":0},{"filename":"route-add-new-loan~route-add-new-product-in-stock~route-addNewSale~route-all-sold-goods-by-user~rout~2f713db3.chunk.*****.esm.js","previous":3942,"size":3942,"diff":0},{"filename":"vendors~route-expenses~route-loans-list~route-report.chunk.*****.esm.js","previous":34426,"size":34426,"diff":0},{"filename":"route-expenses~route-stock.chunk.f4bf1.css","previous":1160,"size":1160,"diff":0},{"filename":"route-expenses~route-stock.chunk.*****.esm.js","previous":5281,"size":5281,"diff":0},{"filename":"route-purchase-logs~route-stock-product-logs.chunk.501ea.css","previous":738,"size":738,"diff":0},{"filename":"route-purchase-logs~route-stock-product-logs.chunk.*****.esm.js","previous":4951,"size":4951,"diff":0},{"filename":"bundle.f49c5.css","previous":4415,"size":4415,"diff":0},{"filename":"route-add-edit-user.chunk.cda21.css","previous":721,"size":721,"diff":0},{"filename":"route-add-edit-user.chunk.*****.esm.js","previous":2797,"size":2797,"diff":0},{"filename":"route-add-new-loan.chunk.fee05.css","previous":1157,"size":1157,"diff":0},{"filename":"route-add-new-loan.chunk.*****.esm.js","previous":5234,"size":5234,"diff":0},{"filename":"route-add-new-product-in-stock.chunk.5ee77.css","previous":805,"size":805,"diff":0},{"filename":"route-add-new-product-in-stock.chunk.*****.esm.js","previous":2446,"size":2446,"diff":0},{"filename":"route-addNewSale.chunk.d8be2.css","previous":776,"size":776,"diff":0},{"filename":"route-addNewSale.chunk.*****.esm.js","previous":2769,"size":2769,"diff":0},{"filename":"route-all-sold-goods-by-user.chunk.a329b.css","previous":2113,"size":2113,"diff":0},{"filename":"route-all-sold-goods-by-user.chunk.*****.esm.js","previous":5877,"size":6009,"diff":132},{"filename":"route-create-account.chunk.ec209.css","previous":911,"size":911,"diff":0},{"filename":"route-create-account.chunk.*****.esm.js","previous":3125,"size":3676,"diff":551},{"filename":"route-customer-loan-detail.chunk.c0f06.css","previous":2456,"size":2456,"diff":0},{"filename":"route-customer-loan-detail.chunk.*****.esm.js","previous":9774,"size":10153,"diff":379},{"filename":"route-dashboard.chunk.c2bb3.css","previous":1276,"size":1276,"diff":0},{"filename":"route-dashboard.chunk.*****.esm.js","previous":79612,"size":79612,"diff":0},{"filename":"route-expenses.chunk.a66f1.css","previous":3094,"size":3094,"diff":0},{"filename":"route-expenses.chunk.*****.esm.js","previous":6807,"size":6916,"diff":109},{"filename":"route-loans-list.chunk.df277.css","previous":2695,"size":2695,"diff":0},{"filename":"route-loans-list.chunk.*****.esm.js","previous":6975,"size":7399,"diff":424},{"filename":"route-login.chunk.57bb1.css","previous":811,"size":811,"diff":0},{"filename":"route-login.chunk.*****.esm.js","previous":1488,"size":1488,"diff":0},{"filename":"route-not-authaurized.chunk.*****.esm.js","previous":250,"size":250,"diff":0},{"filename":"route-products.chunk.5e2f1.css","previous":1667,"size":1667,"diff":0},{"filename":"route-products.chunk.*****.esm.js","previous":5231,"size":5231,"diff":0},{"filename":"route-purchase-logs.chunk.8b4fc.css","previous":1440,"size":1440,"diff":0},{"filename":"route-purchase-logs.chunk.*****.esm.js","previous":2313,"size":2453,"diff":140},{"filename":"route-remove-from-stock.chunk.0cc86.css","previous":792,"size":792,"diff":0},{"filename":"route-remove-from-stock.chunk.*****.esm.js","previous":2174,"size":2174,"diff":0},{"filename":"route-report.chunk.ec3ab.css","previous":1253,"size":1253,"diff":0},{"filename":"route-report.chunk.*****.esm.js","previous":6299,"size":6299,"diff":0},{"filename":"route-sales.chunk.489ed.css","previous":2108,"size":2108,"diff":0},{"filename":"route-sales.chunk.*****.esm.js","previous":6284,"size":6424,"diff":140},{"filename":"route-stock.chunk.8328d.css","previous":1410,"size":1410,"diff":0},{"filename":"route-stock.chunk.*****.esm.js","previous":3397,"size":3603,"diff":206},{"filename":"route-stock-product-logs.chunk.61943.css","previous":1435,"size":1435,"diff":0},{"filename":"route-stock-product-logs.chunk.*****.esm.js","previous":2399,"size":2537,"diff":138},{"filename":"route-users.chunk.55775.css","previous":2142,"size":2142,"diff":0},{"filename":"route-users.chunk.*****.esm.js","previous":5303,"size":5373,"diff":70},{"filename":"assets/icons/icons.js","previous":1599,"size":0,"diff":-1599},{"filename":"route-add-new-loan~route-add-new-product-in-stock~route-addNewSale~route-all-sold-goods-by-user~rout~dffe1d27.chunk.3691d.js","previous":4329,"size":4329,"diff":0},{"filename":"route-add-new-loan~route-add-new-product-in-stock~route-addNewSale~route-all-sold-goods-by-user~rout~2f713db3.chunk.726e5.js","previous":2944,"size":2944,"diff":0},{"filename":"route-add-new-loan~route-customer-loan-detail~route-loans-list.chunk.f7259.js","previous":3122,"size":3122,"diff":0},{"filename":"vendors~route-expenses~route-loans-list~route-report.chunk.be2db.js","previous":34423,"size":34423,"diff":0},{"filename":"route-all-sold-goods-by-user~route-sales.chunk.4b881.css","previous":1085,"size":1085,"diff":0},{"filename":"route-all-sold-goods-by-user~route-sales.chunk.cccb3.js","previous":5763,"size":5763,"diff":0},{"filename":"route-expenses~route-stock.chunk.39e35.js","previous":5681,"size":5681,"diff":0},{"filename":"route-purchase-logs~route-stock-product-logs.chunk.28fda.js","previous":6464,"size":6464,"diff":0},{"filename":"bundle.41524.js","previous":189026,"size":0,"diff":-189026},{"filename":"polyfills.449eb.js","previous":2178,"size":2178,"diff":0},{"filename":"route-add-edit-user.chunk.ea1a4.js","previous":3607,"size":3607,"diff":0},{"filename":"route-add-new-loan.chunk.a3116.js","previous":4878,"size":4878,"diff":0},{"filename":"route-add-new-product-in-stock.chunk.f3c6c.js","previous":3271,"size":3271,"diff":0},{"filename":"route-addNewSale.chunk.49cf2.js","previous":3677,"size":3677,"diff":0},{"filename":"route-all-sold-goods-by-user.chunk.e9ce1.css","previous":1414,"size":1414,"diff":0},{"filename":"route-all-sold-goods-by-user.chunk.4549f.js","previous":2122,"size":0,"diff":-2122},{"filename":"route-create-account.chunk.beec3.js","previous":3533,"size":0,"diff":-3533},{"filename":"route-customer-loan-detail.chunk.c875c.js","previous":7888,"size":0,"diff":-7888},{"filename":"route-dashboard.chunk.ca71b.js","previous":82062,"size":82062,"diff":0},{"filename":"route-expenses.chunk.d9c37.js","previous":9683,"size":0,"diff":-9683},{"filename":"route-loans-list.chunk.02e38.js","previous":6670,"size":0,"diff":-6670},{"filename":"route-login.chunk.afe38.js","previous":1826,"size":1826,"diff":0},{"filename":"route-not-authaurized.chunk.02cfb.js","previous":402,"size":402,"diff":0},{"filename":"route-products.chunk.913cc.js","previous":6615,"size":6615,"diff":0},{"filename":"route-purchase-logs.chunk.8762c.js","previous":2692,"size":0,"diff":-2692},{"filename":"route-remove-from-stock.chunk.f6aa8.js","previous":2841,"size":2841,"diff":0},{"filename":"route-report.chunk.fea9d.js","previous":7892,"size":7892,"diff":0},{"filename":"route-sales.chunk.c2816.css","previous":1408,"size":1408,"diff":0},{"filename":"route-sales.chunk.9ccc5.js","previous":2739,"size":0,"diff":-2739},{"filename":"route-stock.chunk.89dd6.js","previous":2146,"size":0,"diff":-2146},{"filename":"route-stock-product-logs.chunk.084df.js","previous":2809,"size":0,"diff":-2809},{"filename":"route-users.chunk.7419d.js","previous":6671,"size":0,"diff":-6671},{"filename":"bundle.b99f4.js","previous":0,"size":188172,"diff":188172},{"filename":"route-all-sold-goods-by-user.chunk.277b6.js","previous":0,"size":2260,"diff":2260},{"filename":"route-create-account.chunk.fb84d.js","previous":0,"size":4092,"diff":4092},{"filename":"route-customer-loan-detail.chunk.c6f6d.js","previous":0,"size":8246,"diff":8246},{"filename":"route-expenses.chunk.ad188.js","previous":0,"size":9844,"diff":9844},{"filename":"route-loans-list.chunk.ff79e.js","previous":0,"size":7102,"diff":7102},{"filename":"route-purchase-logs.chunk.6d7dd.js","previous":0,"size":2836,"diff":2836},{"filename":"route-sales.chunk.5ba06.js","previous":0,"size":2885,"diff":2885},{"filename":"route-stock.chunk.abc4a.js","previous":0,"size":2346,"diff":2346},{"filename":"route-stock-product-logs.chunk.5d637.js","previous":0,"size":2955,"diff":2955},{"filename":"route-users.chunk.e4afe.js","previous":0,"size":6722,"diff":6722}]},{"timestamp":1622623288660,"files":[{"filename":"bundle.2da73.css","previous":444,"size":0,"diff":-444},{"filename":"bundle.*****.esm.js","previous":8359,"size":187176,"diff":178817},{"filename":"polyfills.*****.esm.js","previous":2181,"size":2182,"diff":1},{"filename":"route-home.chunk.bcb8a.css","previous":75,"size":0,"diff":-75},{"filename":"route-home.chunk.*****.esm.js","previous":253,"size":0,"diff":-253},{"filename":"route-profile.chunk.6dd80.css","previous":78,"size":0,"diff":-78},{"filename":"route-profile.chunk.*****.esm.js","previous":1094,"size":0,"diff":-1094},{"filename":"sw-esm.js","previous":10715,"size":11287,"diff":572},{"filename":"bundle.eb6c4.js","previous":8338,"size":0,"diff":-8338},{"filename":"polyfills.27dd8.js","previous":2178,"size":0,"diff":-2178},{"filename":"route-home.chunk.add00.js","previous":256,"size":0,"diff":-256},{"filename":"route-profile.chunk.3e4c5.js","previous":1101,"size":0,"diff":-1101},{"filename":"index.html","previous":1226,"size":1269,"diff":43},{"filename":"200.html","previous":833,"size":1269,"diff":436},{"filename":"route-add-new-loan~route-add-new-product-in-stock~route-addNewSale~route-all-sold-goods-by-user~rout~2f713db3.chunk.*****.esm.js","previous":0,"size":3942,"diff":3942},{"filename":"vendors~route-expenses~route-loans-list~route-report.chunk.*****.esm.js","previous":0,"size":34426,"diff":34426},{"filename":"route-expenses~route-stock.chunk.f4bf1.css","previous":0,"size":1160,"diff":1160},{"filename":"route-expenses~route-stock.chunk.*****.esm.js","previous":0,"size":5281,"diff":5281},{"filename":"route-purchase-logs~route-stock-product-logs.chunk.501ea.css","previous":0,"size":738,"diff":738},{"filename":"route-purchase-logs~route-stock-product-logs.chunk.*****.esm.js","previous":0,"size":4951,"diff":4951},{"filename":"bundle.f49c5.css","previous":0,"size":4415,"diff":4415},{"filename":"route-add-edit-user.chunk.cda21.css","previous":0,"size":721,"diff":721},{"filename":"route-add-edit-user.chunk.*****.esm.js","previous":0,"size":2797,"diff":2797},{"filename":"route-add-new-loan.chunk.fee05.css","previous":0,"size":1157,"diff":1157},{"filename":"route-add-new-loan.chunk.*****.esm.js","previous":0,"size":5234,"diff":5234},{"filename":"route-add-new-product-in-stock.chunk.5ee77.css","previous":0,"size":805,"diff":805},{"filename":"route-add-new-product-in-stock.chunk.*****.esm.js","previous":0,"size":2446,"diff":2446},{"filename":"route-addNewSale.chunk.d8be2.css","previous":0,"size":776,"diff":776},{"filename":"route-addNewSale.chunk.*****.esm.js","previous":0,"size":2769,"diff":2769},{"filename":"route-all-sold-goods-by-user.chunk.a329b.css","previous":0,"size":2113,"diff":2113},{"filename":"route-all-sold-goods-by-user.chunk.*****.esm.js","previous":0,"size":5877,"diff":5877},{"filename":"route-create-account.chunk.ec209.css","previous":0,"size":911,"diff":911},{"filename":"route-create-account.chunk.*****.esm.js","previous":0,"size":3125,"diff":3125},{"filename":"route-customer-loan-detail.chunk.c0f06.css","previous":0,"size":2456,"diff":2456},{"filename":"route-customer-loan-detail.chunk.*****.esm.js","previous":0,"size":9774,"diff":9774},{"filename":"route-dashboard.chunk.c2bb3.css","previous":0,"size":1276,"diff":1276},{"filename":"route-dashboard.chunk.*****.esm.js","previous":0,"size":79612,"diff":79612},{"filename":"route-expenses.chunk.a66f1.css","previous":0,"size":3094,"diff":3094},{"filename":"route-expenses.chunk.*****.esm.js","previous":0,"size":6807,"diff":6807},{"filename":"route-loans-list.chunk.df277.css","previous":0,"size":2695,"diff":2695},{"filename":"route-loans-list.chunk.*****.esm.js","previous":0,"size":6975,"diff":6975},{"filename":"route-login.chunk.57bb1.css","previous":0,"size":811,"diff":811},{"filename":"route-login.chunk.*****.esm.js","previous":0,"size":1488,"diff":1488},{"filename":"route-not-authaurized.chunk.*****.esm.js","previous":0,"size":250,"diff":250},{"filename":"route-products.chunk.5e2f1.css","previous":0,"size":1667,"diff":1667},{"filename":"route-products.chunk.*****.esm.js","previous":0,"size":5231,"diff":5231},{"filename":"route-purchase-logs.chunk.8b4fc.css","previous":0,"size":1440,"diff":1440},{"filename":"route-purchase-logs.chunk.*****.esm.js","previous":0,"size":2313,"diff":2313},{"filename":"route-remove-from-stock.chunk.0cc86.css","previous":0,"size":792,"diff":792},{"filename":"route-remove-from-stock.chunk.*****.esm.js","previous":0,"size":2174,"diff":2174},{"filename":"route-report.chunk.ec3ab.css","previous":0,"size":1253,"diff":1253},{"filename":"route-report.chunk.*****.esm.js","previous":0,"size":6299,"diff":6299},{"filename":"route-sales.chunk.489ed.css","previous":0,"size":2108,"diff":2108},{"filename":"route-sales.chunk.*****.esm.js","previous":0,"size":6284,"diff":6284},{"filename":"route-stock.chunk.8328d.css","previous":0,"size":1410,"diff":1410},{"filename":"route-stock.chunk.*****.esm.js","previous":0,"size":3397,"diff":3397},{"filename":"route-stock-product-logs.chunk.61943.css","previous":0,"size":1435,"diff":1435},{"filename":"route-stock-product-logs.chunk.*****.esm.js","previous":0,"size":2399,"diff":2399},{"filename":"route-users.chunk.55775.css","previous":0,"size":2142,"diff":2142},{"filename":"route-users.chunk.*****.esm.js","previous":0,"size":5303,"diff":5303},{"filename":"assets/icons/icons.js","previous":0,"size":1599,"diff":1599},{"filename":"route-add-new-loan~route-add-new-product-in-stock~route-addNewSale~route-all-sold-goods-by-user~rout~dffe1d27.chunk.3691d.js","previous":0,"size":4329,"diff":4329},{"filename":"route-add-new-loan~route-add-new-product-in-stock~route-addNewSale~route-all-sold-goods-by-user~rout~2f713db3.chunk.726e5.js","previous":0,"size":2944,"diff":2944},{"filename":"route-add-new-loan~route-customer-loan-detail~route-loans-list.chunk.f7259.js","previous":0,"size":3122,"diff":3122},{"filename":"vendors~route-expenses~route-loans-list~route-report.chunk.be2db.js","previous":0,"size":34423,"diff":34423},{"filename":"route-all-sold-goods-by-user~route-sales.chunk.4b881.css","previous":0,"size":1085,"diff":1085},{"filename":"route-all-sold-goods-by-user~route-sales.chunk.cccb3.js","previous":0,"size":5763,"diff":5763},{"filename":"route-expenses~route-stock.chunk.39e35.js","previous":0,"size":5681,"diff":5681},{"filename":"route-purchase-logs~route-stock-product-logs.chunk.28fda.js","previous":0,"size":6464,"diff":6464},{"filename":"bundle.41524.js","previous":0,"size":189026,"diff":189026},{"filename":"polyfills.449eb.js","previous":0,"size":2178,"diff":2178},{"filename":"route-add-edit-user.chunk.ea1a4.js","previous":0,"size":3607,"diff":3607},{"filename":"route-add-new-loan.chunk.a3116.js","previous":0,"size":4878,"diff":4878},{"filename":"route-add-new-product-in-stock.chunk.f3c6c.js","previous":0,"size":3271,"diff":3271},{"filename":"route-addNewSale.chunk.49cf2.js","previous":0,"size":3677,"diff":3677},{"filename":"route-all-sold-goods-by-user.chunk.e9ce1.css","previous":0,"size":1414,"diff":1414},{"filename":"route-all-sold-goods-by-user.chunk.4549f.js","previous":0,"size":2122,"diff":2122},{"filename":"route-create-account.chunk.beec3.js","previous":0,"size":3533,"diff":3533},{"filename":"route-customer-loan-detail.chunk.c875c.js","previous":0,"size":7888,"diff":7888},{"filename":"route-dashboard.chunk.ca71b.js","previous":0,"size":82062,"diff":82062},{"filename":"route-expenses.chunk.d9c37.js","previous":0,"size":9683,"diff":9683},{"filename":"route-loans-list.chunk.02e38.js","previous":0,"size":6670,"diff":6670},{"filename":"route-login.chunk.afe38.js","previous":0,"size":1826,"diff":1826},{"filename":"route-not-authaurized.chunk.02cfb.js","previous":0,"size":402,"diff":402},{"filename":"route-products.chunk.913cc.js","previous":0,"size":6615,"diff":6615},{"filename":"route-purchase-logs.chunk.8762c.js","previous":0,"size":2692,"diff":2692},{"filename":"route-remove-from-stock.chunk.f6aa8.js","previous":0,"size":2841,"diff":2841},{"filename":"route-report.chunk.fea9d.js","previous":0,"size":7892,"diff":7892},{"filename":"route-sales.chunk.c2816.css","previous":0,"size":1408,"diff":1408},{"filename":"route-sales.chunk.9ccc5.js","previous":0,"size":2739,"diff":2739},{"filename":"route-stock.chunk.89dd6.js","previous":0,"size":2146,"diff":2146},{"filename":"route-stock-product-logs.chunk.084df.js","previous":0,"size":2809,"diff":2809},{"filename":"route-users.chunk.7419d.js","previous":0,"size":6671,"diff":6671}]},{"timestamp":1622499331303,"files":[{"filename":"ssr-build/ssr-bundle.aaacf.css","previous":564,"size":0,"diff":-564},{"filename":"ssr-build/ssr-bundle.js","previous":4047,"size":0,"diff":-4047},{"filename":"bundle.2da73.css","previous":0,"size":444,"diff":444},{"filename":"bundle.*****.esm.js","previous":0,"size":8359,"diff":8359},{"filename":"polyfills.*****.esm.js","previous":0,"size":2181,"diff":2181},{"filename":"route-home.chunk.bcb8a.css","previous":0,"size":75,"diff":75},{"filename":"route-home.chunk.*****.esm.js","previous":0,"size":253,"diff":253},{"filename":"route-profile.chunk.6dd80.css","previous":0,"size":78,"diff":78},{"filename":"route-profile.chunk.*****.esm.js","previous":0,"size":1094,"diff":1094},{"filename":"sw-esm.js","previous":0,"size":10715,"diff":10715},{"filename":"bundle.eb6c4.js","previous":0,"size":8338,"diff":8338},{"filename":"polyfills.27dd8.js","previous":0,"size":2178,"diff":2178},{"filename":"route-home.chunk.add00.js","previous":0,"size":256,"diff":256},{"filename":"route-profile.chunk.3e4c5.js","previous":0,"size":1101,"diff":1101},{"filename":"index.html","previous":0,"size":1226,"diff":1226},{"filename":"200.html","previous":0,"size":833,"diff":833}]}]
